{
    "dappDirectory_title": "dApp Directory",
    "dappDirectory_search_placeholder": "Search for a dApp...",
    "dappDirectory_filters_title": "Tags",
    "dappDirectory_error_heading": "Failed to load dApps.",
    "dappDirectory_error_message": "Pull to refresh",
    "dappDirectory_empty_message": "There are no dApps available on this network.",
    "dappDirectory_categoryDefi_title": "DeFi",
    "dappDirectory_categoryUtility_title": "Utility",
    "dappDirectory_categoryDao_title": "Dao",
    "dappDirectory_categoryNFT_title": "NFT",
    "dappDirectory_categoryMeme_title": "Meme",
    "dappDirectory_categoryOther_title": "Other",
    "dappDirectory_viewAllDApps": "All dApps",
    "dappDirectory_viewConnectedDApps": "Connected dApps"
}
